{
  "appName": "Microsoft Outlook.app",
  "bundleId": "com.microsoft.Outlook",
  "currentVersion": "16.19.18110915",
  "extensionAttributes": [
  ],
  "id": "MicrosoftOutlook2019-msupdate",
  "lastModified": "2018-11-27T15:34:52Z",
  "name": "Microsoft Outlook 2019 (msupdate)",
  "patches": [
    {
      "capabilities": [
        {
          "and": true,
          "name": "Operating System Version",
          "operator": "greater than or equal",
          "type": "recon",
          "value": "10.12"
        }
      ],
      "components": [
        {
          "criteria": [
            {
              "and": true,
              "name": "Application Version",
              "operator": "is",
              "type": "recon",
              "value": "16.19.18110915"
            },
            {
              "and": true,
              "name": "Application Bundle ID",
              "operator": "is",
              "type": "recon",
              "value": "com.microsoft.Outlook"
            }
          ],
          "name": "Microsoft Outlook 2019",
          "version": "16.19.18110915"
        }
      ],
      "killApps": [
        {
          "appName": "Microsoft Dummy.app",
          "bundleId": "com.microsoft.Dummy"
        }
      ],
      "minimumOperatingSystem": "10.12",
      "reboot": false,
      "releaseDate": "2018-11-14T19:49:22Z",
      "standalone": true,
      "version": "16.19.18110915"
    },
    {
      "capabilities": [
        {
          "and": true,
          "name": "Operating System Version",
          "operator": "greater than or equal",
          "type": "recon",
          "value": "10.12"
        }
      ],
      "components": [
        {
          "criteria": [
            {
              "and": true,
              "name": "Application Version",
              "operator": "is",
              "type": "recon",
              "value": "16.18.18101400"
            },
            {
              "and": true,
              "name": "Application Bundle ID",
              "operator": "is",
              "type": "recon",
              "value": "com.microsoft.Outlook"
            }
          ],
          "name": "Microsoft Outlook 2019",
          "version": "16.18.18101400"
        }
      ],
      "killApps": [
        {
          "appName": "Microsoft Dummy.app",
          "bundleId": "com.microsoft.Dummy"
        }
      ],
      "minimumOperatingSystem": "10.12",
      "reboot": false,
      "releaseDate": "2018-10-17T18:51:37Z",
      "standalone": true,
      "version": "16.18.18101400"
    },
    {
      "capabilities": [
        {
          "and": true,
          "name": "Operating System Version",
          "operator": "greater than or equal",
          "type": "recon",
          "value": "10.12"
        }
      ],
      "components": [
        {
          "criteria": [
            {
              "and": true,
              "name": "Application Version",
              "operator": "is",
              "type": "recon",
              "value": "16.17.18090901"
            },
            {
              "and": true,
              "name": "Application Bundle ID",
              "operator": "is",
              "type": "recon",
              "value": "com.microsoft.Outlook"
            }
          ],
          "name": "Microsoft Outlook 2019",
          "version": "16.17.18090901"
        }
      ],
      "killApps": [
        {
          "appName": "Microsoft Dummy.app",
          "bundleId": "com.microsoft.Dummy"
        }
      ],
      "minimumOperatingSystem": "10.12",
      "reboot": false,
      "releaseDate": "2018-09-13T15:50:54Z",
      "standalone": true,
      "version": "16.17.18090901"
    }
  ],
  "publisher": "Microsoft",
  "requirements": [
    {
      "and": true,
      "name": "Application Bundle ID",
      "operator": "is",
      "type": "recon",
      "value": "com.microsoft.Outlook"
    },
    {
      "and": false,
      "name": "Application Version",
      "operator": "like",
      "type": "recon",
      "value": "16."
    }
  ]
}
